[
  {"author": "J.R.R. Tolkien",
    "title": "Pán prstenů: Dvě věže",
    "itemId": 123
  },
  {"author": "J.R.R. Tolkien",
    "title": "Pán prstenů: Společenstvo prstenu",
    "itemId": 1231
  },
  {"author": "J.R.R. Tolkien",
    "title": "Pán prstenů: Návrat krále",
    "itemId": 12313
  },
  {"author": "J.R.R. Tolkien",
    "title": "Silmarilion",
    "itemId": 123134
  },
  {"author": "J.R.R. Tolkien",
    "title": "Hobit",
    "itemId": 1231345
  },
  {"author": "Terry Pratchet",
    "title": "Úžasná Zeměplocha",
    "itemId": 12313456
  }
]